.coveragerc
.flake8
.gitignore
.travis.yml
CHANGELOG.md
CONTRIBUTING.md
LICENSE
MANIFEST.in
Makefile
README.md
pytest.ini
release.md
requirements.txt
setup.py
bam2fasta/__init__.py
bam2fasta/__main__.py
bam2fasta/bam2fasta_args.py
bam2fasta/cli.py
bam2fasta/tenx_utils.py
bam2fasta/version.py
bam2fasta.egg-info/PKG-INFO
bam2fasta.egg-info/SOURCES.txt
bam2fasta.egg-info/dependency_links.txt
bam2fasta.egg-info/entry_points.txt
bam2fasta.egg-info/requires.txt
bam2fasta.egg-info/top_level.txt
bam2fasta/tests/__init__.py
bam2fasta/tests/bam2fasta_tst_utils.py
bam2fasta/tests/test_bam2fasta.py
bam2fasta/tests/test_bam2fasta_args.py
bam2fasta/tests/test_tenx_utils.py
bam2fasta/tests/test-data/10x-example/barcodes.tsv
bam2fasta/tests/test-data/10x-example/barcodes_renamer.tsv
bam2fasta/tests/test-data/10x-example/good_barcodes.csv
bam2fasta/tests/test-data/10x-example/groundtruth_fasta_sequences.txt
bam2fasta/tests/test-data/10x-example/possorted_genome_bam.bam
bam2fasta/tests/test-data/10x-example/possorted_genome_bam.bam.bai
bam2fasta/tests/test-data/10x-example/possorted_genome_bam.fastq.gz
bam2fasta/tests/test-data/10x-example/possorted_genome_bam_filtered.bam
bam2fasta/tests/test-data/10x-example/possorted_genome_bam_unaligned_seqs.bam
paper/bam2fasta_workflow.png
paper/paper.bib
paper/paper.md