Metadata-Version: 2.1
Name: bam2fasta
Version: 1.0.7
Summary: tool for converting a bam file to fastas
Home-page: https://github.com/czbiohub/bam2fasta
Author: Pranathi Vemuri
Author-email: pranathi93.vemuri@gmail.com
Maintainer: Pranathi Vemuri
Maintainer-email: pranathi93.vemuri@gmail.com
License: MIT License
Keywords: 10x,bam,genomic,fastas,kmers,sequences
Platform: UNKNOWN
Classifier: Environment :: Console
Classifier: Environment :: MacOS X
Classifier: Intended Audience :: Science/Research
Classifier: License :: OSI Approved :: MIT License
Classifier: Natural Language :: English
Classifier: Operating System :: POSIX :: Linux
Classifier: Operating System :: MacOS :: MacOS X
Classifier: Programming Language :: C++
Classifier: Programming Language :: Python :: 2.7
Classifier: Programming Language :: Python :: 3.5
Classifier: Programming Language :: Python :: 3.6
Classifier: Programming Language :: Python :: 3.7
Classifier: Topic :: Scientific/Engineering :: Bio-Informatics
Classifier: Development Status :: 5 - Production/Stable
Provides-Extra: test
